<annotation>
	<folder>cars_train</folder>
	<filename>00160.jpg</filename>
	<path>I:\Centre d'Estudis Monlau\FÉLIX CALVO DÍAZ DE CERIO - Proyecto\Proyecto2\Proyecto\cars_train\00160.jpg</path>
	<source>
		<database>Unknown</database>
	</source>
	<size>
		<width>625</width>
		<height>350</height>
		<depth>3</depth>
	</size>
	<segmented>0</segmented>
	<object>
		<name>car</name>
		<pose>Unspecified</pose>
		<truncated>0</truncated>
		<difficult>0</difficult>
		<bndbox>
			<xmin>116</xmin>
			<ymin>49</ymin>
			<xmax>544</xmax>
			<ymax>284</ymax>
		</bndbox>
	</object>
</annotation>
